tests/__init__.py
tests/test_wikidatasets.py
wikidatasets/__init__.py
wikidatasets/exceptions.py
wikidatasets/processFunctions.py
wikidatasets/utils.py
wikidatasets-0.3.0.dist-info/LICENSE
wikidatasets-0.3.0.dist-info/METADATA
wikidatasets-0.3.0.dist-info/WHEEL
wikidatasets-0.3.0.dist-info/top_level.txt
wikidatasets-0.3.0.dist-info/RECORD
