Metadata-Version: 2.1
Name: wikidatasets
Version: 0.3.0
Summary: Break WikiData dumps into smaller knowledge graphs
Home-page: https://github.com/armand33/wikidatasets
Author: Armand Boschin
Author-email: aboschin@enst.fr
License: BSD license
Keywords: wikidatasets
Platform: UNKNOWN
Classifier: Development Status :: 2 - Pre-Alpha
Classifier: Intended Audience :: Developers
Classifier: License :: OSI Approved :: BSD License
Classifier: Natural Language :: English
Classifier: Programming Language :: Python :: 3.7
Requires-Dist: tqdm (>=4.43)
Requires-Dist: sparqlwrapper (>=1.8.5)
Requires-Dist: pandas (>=1.0.3)
